.gitignore
MANIFEST.in
README.rst
setup.cfg
setup.py
docs/HISTORY.txt
docs/LICENSE.GPL
docs/LICENSE.txt
docs/MANUAL.txt
raptus/__init__.py
raptus.article.lightbox.egg-info/PKG-INFO
raptus.article.lightbox.egg-info/SOURCES.txt
raptus.article.lightbox.egg-info/dependency_links.txt
raptus.article.lightbox.egg-info/entry_points.txt
raptus.article.lightbox.egg-info/namespace_packages.txt
raptus.article.lightbox.egg-info/not-zip-safe
raptus.article.lightbox.egg-info/requires.txt
raptus.article.lightbox.egg-info/top_level.txt
raptus/article/__init__.py
raptus/article/lightbox/__init__.py
raptus/article/lightbox/configure.zcml
raptus/article/lightbox/browser/__init__.py
raptus/article/lightbox/browser/configure.zcml
raptus/article/lightbox/browser/lightbox.gif
raptus/article/lightbox/browser/lightbox.pt
raptus/article/lightbox/browser/lightbox.py
raptus/article/lightbox/browser/lightbox_teaser.gif
raptus/article/lightbox/i18n/raptus.article-de.mo
raptus/article/lightbox/i18n/raptus.article-de.po
raptus/article/lightbox/i18n/raptus.article-fr.mo
raptus/article/lightbox/i18n/raptus.article-fr.po
raptus/article/lightbox/i18n/raptus.article.pot
raptus/article/lightbox/profiles/default/metadata.xml
raptus/article/lightbox/profiles/default/propertiestool.xml
raptus/article/lightbox/profiles/default/viewlets.xml