Metadata-Version: 1.1
Name: raptus.article.lightbox
Version: 2.0b6
Summary: Provides an inline lightbox component showing the images contained in the article.
Home-page: https://github.com/Raptus/raptus.article.lightbox
Author: Raptus AG
Author-email: dev@raptus.com
License: GPL
Platform: UNKNOWN
Classifier: Programming Language :: Python
Classifier: Topic :: Software Development :: Libraries :: Python Modules
